{"id":1,"name":"admin","url":"https:\/\/themexriver.com\/appilo-theme","description":"","link":"https:\/\/themexriver.com\/appilo-theme\/it-solution\/?author=1","slug":"admin","avatar_urls":{"24":"https:\/\/secure.gravatar.com\/avatar\/9855b85c8526972b8cb3a82ebe7a17d4?s=24&d=mm&r=g","48":"https:\/\/secure.gravatar.com\/avatar\/9855b85c8526972b8cb3a82ebe7a17d4?s=48&d=mm&r=g","96":"https:\/\/secure.gravatar.com\/avatar\/9855b85c8526972b8cb3a82ebe7a17d4?s=96&d=mm&r=g"},"meta":[],"_links":{"self":[{"href":"https:\/\/themexriver.com\/appilo-theme\/it-solution\/index.php?rest_route=\/wp\/v2\/users\/1"}],"collection":[{"href":"https:\/\/themexriver.com\/appilo-theme\/it-solution\/index.php?rest_route=\/wp\/v2\/users"}]}}